{
  "paloAltoToSF": [
    {"time": "05:10", "train": "101", "type": "Local"},
    {"time": "05:35", "train": "103", "type": "Local"},
    {"time": "06:10", "train": "105", "type": "Local"},
    {"time": "06:25", "train": "107", "type": "Local"},
    {"time": "06:43", "train": "503", "type": "Express"},
    {"time": "06:55", "train": "109", "type": "Local"},
    {"time": "07:10", "train": "111", "type": "Local"},
    {"time": "07:25", "train": "113", "type": "Local"},
    {"time": "07:43", "train": "507", "type": "Express"},
    {"time": "07:55", "train": "115", "type": "Local"},
    {"time": "08:10", "train": "117", "type": "Local"},
    {"time": "08:25", "train": "119", "type": "Local"},
    {"time": "08:43", "train": "511", "type": "Express"},
    {"time": "08:55", "train": "121", "type": "Local"},
    {"time": "09:11", "train": "123", "type": "Local"},
    {"time": "09:25", "train": "125", "type": "Local"},
    {"time": "09:55", "train": "127", "type": "Local"},
    {"time": "10:25", "train": "129", "type": "Local"},
    {"time": "10:55", "train": "131", "type": "Local"},
    {"time": "11:25", "train": "133", "type": "Local"},
    {"time": "11:55", "train": "135", "type": "Local"},
    {"time": "12:25", "train": "137", "type": "Local"},
    {"time": "12:55", "train": "139", "type": "Local"},
    {"time": "13:25", "train": "141", "type": "Local"},
    {"time": "13:55", "train": "143", "type": "Local"},
    {"time": "14:25", "train": "145", "type": "Local"},
    {"time": "14:55", "train": "147", "type": "Local"},
    {"time": "15:25", "train": "149", "type": "Local"},
    {"time": "15:43", "train": "515", "type": "Express"},
    {"time": "15:55", "train": "151", "type": "Local"},
    {"time": "16:10", "train": "417", "type": "Limited"},
    {"time": "16:25", "train": "153", "type": "Local"},
    {"time": "16:43", "train": "519", "type": "Express"},
    {"time": "16:55", "train": "155", "type": "Local"},
    {"time": "17:10", "train": "421", "type": "Limited"},
    {"time": "17:25", "train": "157", "type": "Local"},
    {"time": "17:43", "train": "523", "type": "Express"},
    {"time": "17:55", "train": "159", "type": "Local"},
    {"time": "18:10", "train": "425", "type": "Limited"},
    {"time": "18:25", "train": "161", "type": "Local"},
    {"time": "18:43", "train": "527", "type": "Express"},
    {"time": "18:55", "train": "163", "type": "Local"},
    {"time": "19:10", "train": "429", "type": "Limited"},
    {"time": "19:25", "train": "165", "type": "Local"},
    {"time": "19:55", "train": "167", "type": "Local"},
    {"time": "20:25", "train": "169", "type": "Local"},
    {"time": "20:55", "train": "171", "type": "Local"},
    {"time": "21:25", "train": "173", "type": "Local"},
    {"time": "21:55", "train": "175", "type": "Local"},
    {"time": "22:25", "train": "177", "type": "Local"},
    {"time": "22:57", "train": "179", "type": "Local"},
    {"time": "23:57", "train": "181", "type": "Local"}
  ],
  "sfToPaloAlto": [
    {"time": "05:44", "train": "102", "type": "Local"},
    {"time": "06:24", "train": "104", "type": "Local"},
    {"time": "06:59", "train": "502", "type": "Express"},
    {"time": "07:14", "train": "106", "type": "Local"},
    {"time": "07:29", "train": "404", "type": "Limited"},
    {"time": "07:44", "train": "108", "type": "Local"},
    {"time": "07:59", "train": "506", "type": "Express"},
    {"time": "08:14", "train": "110", "type": "Local"},
    {"time": "08:29", "train": "408", "type": "Limited"},
    {"time": "08:44", "train": "112", "type": "Local"},
    {"time": "08:59", "train": "510", "type": "Express"},
    {"time": "09:14", "train": "114", "type": "Local"},
    {"time": "09:29", "train": "412", "type": "Limited"},
    {"time": "09:44", "train": "116", "type": "Local"},
    {"time": "10:14", "train": "118", "type": "Local"},
    {"time": "10:44", "train": "120", "type": "Local"},
    {"time": "11:14", "train": "122", "type": "Local"},
    {"time": "11:44", "train": "124", "type": "Local"},
    {"time": "12:14", "train": "126", "type": "Local"},
    {"time": "12:44", "train": "128", "type": "Local"},
    {"time": "13:14", "train": "130", "type": "Local"},
    {"time": "13:44", "train": "132", "type": "Local"},
    {"time": "14:14", "train": "134", "type": "Local"},
    {"time": "14:44", "train": "136", "type": "Local"},
    {"time": "15:14", "train": "138", "type": "Local"},
    {"time": "15:44", "train": "140", "type": "Local"},
    {"time": "15:59", "train": "514", "type": "Express"},
    {"time": "16:14", "train": "142", "type": "Local"},
    {"time": "16:29", "train": "416", "type": "Limited"},
    {"time": "16:44", "train": "144", "type": "Local"},
    {"time": "16:59", "train": "518", "type": "Express"},
    {"time": "17:14", "train": "146", "type": "Local"},
    {"time": "17:29", "train": "420", "type": "Limited"},
    {"time": "17:44", "train": "148", "type": "Local"},
    {"time": "17:59", "train": "522", "type": "Express"},
    {"time": "18:14", "train": "150", "type": "Local"},
    {"time": "18:29", "train": "424", "type": "Limited"},
    {"time": "18:44", "train": "152", "type": "Local"},
    {"time": "18:59", "train": "526", "type": "Express"},
    {"time": "19:14", "train": "154", "type": "Local"},
    {"time": "19:29", "train": "428", "type": "Limited"},
    {"time": "19:44", "train": "156", "type": "Local"},
    {"time": "20:14", "train": "158", "type": "Local"},
    {"time": "20:44", "train": "160", "type": "Local"},
    {"time": "21:14", "train": "162", "type": "Local"},
    {"time": "21:44", "train": "164", "type": "Local"},
    {"time": "22:14", "train": "166", "type": "Local"},
    {"time": "22:44", "train": "168", "type": "Local"},
    {"time": "23:14", "train": "170", "type": "Local"},
    {"time": "23:44", "train": "172", "type": "Local"},
    {"time": "00:14", "train": "174", "type": "Local"},
    {"time": "00:54", "train": "176", "type": "Local"}
  ]
}